pymwp/__init__.py
pymwp/__main__.py
pymwp/analysis.py
pymwp/bound.py
pymwp/choice.py
pymwp/constants.py
pymwp/delta_graphs.py
pymwp/file_io.py
pymwp/matrix.py
pymwp/monomial.py
pymwp/parser.py
pymwp/polynomial.py
pymwp/relation.py
pymwp/relation_list.py
pymwp/result.py
pymwp/semiring.py
pymwp/syntax.py
pymwp/version.py
pymwp-0.5.5.dist-info/licenses/LICENSE
pymwp-0.5.5.dist-info/METADATA
pymwp-0.5.5.dist-info/WHEEL
pymwp-0.5.5.dist-info/entry_points.txt
pymwp-0.5.5.dist-info/top_level.txt
pymwp-0.5.5.dist-info/RECORD
