Metadata-Version: 2.4
Name: pymwp
Version: 0.5.5
Summary: Implementation of MWP analysis on C code in Python.
Home-page: https://github.com/statycc/pymwp
Author: Clément Aubert, Thomas Rubiano, Neea Rusch, Thomas Seiller
Author-email: nrusch@augusta.edu
License: GPLv3+
Project-URL: Bug Tracker, https://github.com/statycc/pymwp/issues
Project-URL: Documentation, https://statycc.github.io/pymwp/
Project-URL: Source Code, https://github.com/statycc/pymwp
Project-URL: Archive, https://doi.org/10.5281/zenodo.7879822
Classifier: Natural Language :: English
Classifier: Intended Audience :: Science/Research
Classifier: Development Status :: 4 - Beta
Classifier: Programming Language :: Python
Classifier: Programming Language :: Python :: 3
Classifier: Programming Language :: Python :: 3.7
Classifier: Programming Language :: Python :: 3.8
Classifier: Programming Language :: Python :: 3.9
Classifier: Programming Language :: Python :: 3.10
Classifier: Programming Language :: Python :: 3.11
Classifier: Programming Language :: Python :: 3.12
Classifier: Operating System :: OS Independent
Classifier: Environment :: Console
Classifier: Typing :: Typed
Classifier: Topic :: Scientific/Engineering
Classifier: Topic :: Software Development
Classifier: License :: OSI Approved :: GNU General Public License v3 or later (GPLv3+)
Requires-Python: >=3.7
License-File: LICENSE
Requires-Dist: pycparser
Requires-Dist: pycparser-fake-libc
Dynamic: author
Dynamic: author-email
Dynamic: classifier
Dynamic: description
Dynamic: description-content-type
Dynamic: home-page
Dynamic: license
Dynamic: license-file
Dynamic: project-url
Dynamic: requires-dist
Dynamic: requires-python
Dynamic: summary
